cite_agent/__init__.py
cite_agent/__main__.py
cite_agent/__version__.py
cite_agent/account_client.py
cite_agent/adaptive_providers.py
cite_agent/advanced_statistics.py
cite_agent/ascii_plotting.py
cite_agent/auth.py
cite_agent/circuit_breaker.py
cite_agent/cli.py
cite_agent/cli_workflow.py
cite_agent/conversation_archive.py
cite_agent/dashboard.py
cite_agent/data_cleaning_magic.py
cite_agent/enhanced_ai_agent.py
cite_agent/execution_safety.py
cite_agent/function_calling.py
cite_agent/function_tools.py
cite_agent/literature_synthesis.py
cite_agent/observability.py
cite_agent/power_analysis.py
cite_agent/project_detector.py
cite_agent/prometheus_metrics.py
cite_agent/qualitative_coding.py
cite_agent/r_workspace_bridge.py
cite_agent/rate_limiter.py
cite_agent/request_queue.py
cite_agent/research_assistant.py
cite_agent/self_healing.py
cite_agent/session_manager.py
cite_agent/session_memory_manager.py
cite_agent/setup_config.py
cite_agent/streaming_ui.py
cite_agent/telemetry.py
cite_agent/timeout_retry_handler.py
cite_agent/tool_executor.py
cite_agent/unified_observability.py
cite_agent/updater.py
cite_agent/web_search.py
cite_agent/workflow.py
cite_agent/workflow_integration.py
cite_agent-1.5.2.dist-info/licenses/LICENSE
cite_agent-1.5.2.dist-info/METADATA
cite_agent-1.5.2.dist-info/WHEEL
cite_agent-1.5.2.dist-info/entry_points.txt
cite_agent-1.5.2.dist-info/top_level.txt
cite_agent-1.5.2.dist-info/RECORD
